exonware/__init__.py
exonware/conf.py
exonware/xwsystem/__init__.py
exonware/xwsystem/conf.py
exonware/xwsystem/version.py
exonware/xwsystem/caching/__init__.py
exonware/xwsystem/caching/base.py
exonware/xwsystem/caching/bloom_cache.py
exonware/xwsystem/caching/cache_manager.py
exonware/xwsystem/caching/conditional.py
exonware/xwsystem/caching/contracts.py
exonware/xwsystem/caching/decorators.py
exonware/xwsystem/caching/defs.py
exonware/xwsystem/caching/disk_cache.py
exonware/xwsystem/caching/distributed.py
exonware/xwsystem/caching/errors.py
exonware/xwsystem/caching/events.py
exonware/xwsystem/caching/eviction_strategies.py
exonware/xwsystem/caching/fluent.py
exonware/xwsystem/caching/integrity.py
exonware/xwsystem/caching/lfu_cache.py
exonware/xwsystem/caching/lfu_optimized.py
exonware/xwsystem/caching/lru_cache.py
exonware/xwsystem/caching/memory_bounded.py
exonware/xwsystem/caching/metrics_exporter.py
exonware/xwsystem/caching/observable_cache.py
exonware/xwsystem/caching/pluggable_cache.py
exonware/xwsystem/caching/rate_limiter.py
exonware/xwsystem/caching/read_through.py
exonware/xwsystem/caching/secure_cache.py
exonware/xwsystem/caching/serializable.py
exonware/xwsystem/caching/stats.py
exonware/xwsystem/caching/tagging.py
exonware/xwsystem/caching/ttl_cache.py
exonware/xwsystem/caching/two_tier_cache.py
exonware/xwsystem/caching/utils.py
exonware/xwsystem/caching/validation.py
exonware/xwsystem/caching/warming.py
exonware/xwsystem/caching/write_behind.py
exonware/xwsystem/cli/__init__.py
exonware/xwsystem/cli/args.py
exonware/xwsystem/cli/base.py
exonware/xwsystem/cli/colors.py
exonware/xwsystem/cli/console.py
exonware/xwsystem/cli/contracts.py
exonware/xwsystem/cli/defs.py
exonware/xwsystem/cli/errors.py
exonware/xwsystem/cli/progress.py
exonware/xwsystem/cli/prompts.py
exonware/xwsystem/cli/tables.py
exonware/xwsystem/config/__init__.py
exonware/xwsystem/config/base.py
exonware/xwsystem/config/contracts.py
exonware/xwsystem/config/defaults.py
exonware_xwsystem-0.1.0.1.dist-info/METADATA
exonware_xwsystem-0.1.0.1.dist-info/WHEEL
exonware_xwsystem-0.1.0.1.dist-info/licenses/LICENSE
exonware_xwsystem-0.1.0.1.dist-info/RECORD
