Metadata-Version: 2.4
Name: exonware-xwsystem
Version: 0.1.0.1
Summary: Enterprise-grade Python framework with AI-powered performance optimization, 24 serialization formats, military-grade security, automatic memory leak prevention, circuit breakers, and production monitoring - replaces 50+ dependencies
Project-URL: Homepage, https://exonware.com
Project-URL: Repository, https://github.com/exonware/xwsystem
Project-URL: Documentation, https://github.com/exonware/xwsystem#readme
Author-email: "Eng. Muhammad AlShehri" <connect@exonware.com>
License: MIT
License-File: LICENSE
Keywords: ai-optimization,bson,cbor,circuit-breaker,crypto,enterprise,exonware,framework,json,memory-management,monitoring,msgpack,object-pool,performance,security,serialization,threading,yaml
Classifier: Development Status :: 4 - Beta
Classifier: Intended Audience :: Developers
Classifier: Intended Audience :: Information Technology
Classifier: Intended Audience :: System Administrators
Classifier: License :: OSI Approved :: MIT License
Classifier: Operating System :: OS Independent
Classifier: Programming Language :: Python :: 3
Classifier: Programming Language :: Python :: 3.12
Classifier: Topic :: Database
Classifier: Topic :: Internet :: WWW/HTTP
Classifier: Topic :: Security :: Cryptography
Classifier: Topic :: Software Development :: Libraries :: Python Modules
Classifier: Topic :: System :: Monitoring
Classifier: Topic :: System :: Systems Administration
Requires-Python: >=3.12
Requires-Dist: typing-extensions>=4.0.0
Provides-Extra: full
Requires-Dist: aiofiles>=0.8.0; extra == 'full'
Requires-Dist: bcrypt>=4.0.0; extra == 'full'
Requires-Dist: cbor2>=5.0.0; extra == 'full'
Requires-Dist: colorama>=0.4.0; extra == 'full'
Requires-Dist: cryptography>=3.4.0; extra == 'full'
Requires-Dist: defusedxml>=0.7.0; extra == 'full'
Requires-Dist: dicttoxml>=1.7.0; extra == 'full'
Requires-Dist: fastavro>=1.4.0; extra == 'full'
Requires-Dist: httpx>=0.24.0; extra == 'full'
Requires-Dist: ijson>=3.2.0; extra == 'full'
Requires-Dist: json5>=0.9.0; extra == 'full'
Requires-Dist: jsonpatch>=1.33.0; extra == 'full'
Requires-Dist: jsonpath-ng>=1.6.0; extra == 'full'
Requires-Dist: jsonpointer>=2.0.0; extra == 'full'
Requires-Dist: jsonschema>=4.17.0; extra == 'full'
Requires-Dist: lxml>=4.9.0; extra == 'full'
Requires-Dist: msgpack>=1.0.0; extra == 'full'
Requires-Dist: msgspec>=0.11.0; extra == 'full'
Requires-Dist: opentelemetry-api>=1.20.0; extra == 'full'
Requires-Dist: opentelemetry-sdk>=1.20.0; extra == 'full'
Requires-Dist: orjson>=3.8.0; extra == 'full'
Requires-Dist: protobuf>=3.19.0; extra == 'full'
Requires-Dist: psutil>=5.8.0; extra == 'full'
Requires-Dist: pyarrow>=8.0.0; extra == 'full'
Requires-Dist: pyjwt>=2.6.0; extra == 'full'
Requires-Dist: pymongo>=3.12.0; extra == 'full'
Requires-Dist: pytz>=2023.3; extra == 'full'
Requires-Dist: pyyaml-include>=1.3.0; extra == 'full'
Requires-Dist: pyyaml>=5.4.0; extra == 'full'
Requires-Dist: requests>=2.28.0; extra == 'full'
Requires-Dist: rpds-py>=0.10.0; extra == 'full'
Requires-Dist: rtoml>=0.7.0; extra == 'full'
Requires-Dist: ruamel-yaml>=0.17.0; extra == 'full'
Requires-Dist: thrift>=0.10.0; extra == 'full'
Requires-Dist: tomli-w>=1.0.0; extra == 'full'
Requires-Dist: tomli>=2.0.0; extra == 'full'
Requires-Dist: xmlschema>=2.0.0; extra == 'full'
Requires-Dist: xmltodict>=0.13.0; extra == 'full'
Requires-Dist: xxhash>=3.2.0; extra == 'full'
